evoxels/__init__.py
evoxels/boundary_conditions.py
evoxels/fd_stencils.py
evoxels/function_approximators.py
evoxels/inversion.py
evoxels/problem_definition.py
evoxels/profiler.py
evoxels/solvers.py
evoxels/timesteppers.py
evoxels/utils.py
evoxels/voxelfields.py
evoxels/voxelgrid.py
evoxels/precompiled_solvers/__init__.py
evoxels/precompiled_solvers/allen_cahn.py
evoxels/precompiled_solvers/cahn_hilliard.py
evoxels-0.1.2.dist-info/licenses/LICENSE
evoxels-0.1.2.dist-info/METADATA
evoxels-0.1.2.dist-info/WHEEL
evoxels-0.1.2.dist-info/top_level.txt
evoxels-0.1.2.dist-info/RECORD
