Metadata-Version: 2.4
Name: evoxels
Version: 0.1.2
Summary: Differentiable physics framework for voxel-based microstructure simulations
Author-email: Simon Daubner <s.daubner@imperial.ac.uk>
License: MIT
Classifier: Development Status :: 4 - Beta
Classifier: Intended Audience :: Science/Research
Classifier: Topic :: Scientific/Engineering :: Physics
Classifier: Topic :: Scientific/Engineering :: Chemistry
Classifier: Topic :: Scientific/Engineering :: Image Processing
Classifier: License :: OSI Approved :: MIT License
Classifier: Natural Language :: English
Classifier: Environment :: GPU
Classifier: Environment :: GPU :: NVIDIA CUDA
Classifier: Programming Language :: Python :: 3
Classifier: Programming Language :: Python :: 3.9
Classifier: Programming Language :: Python :: 3.10
Classifier: Programming Language :: Python :: 3.11
Classifier: Programming Language :: Python :: 3.12
Requires-Python: >=3.9
License-File: LICENSE
Requires-Dist: numpy>=1.21
Requires-Dist: matplotlib>=3.4
Requires-Dist: pyvista>=0.38
Requires-Dist: psutil>=5.9.0
Requires-Dist: ipython>=7.0.0
Requires-Dist: sympy>=1.10
Provides-Extra: torch
Requires-Dist: torch>=2.1; extra == "torch"
Provides-Extra: jax
Requires-Dist: jax>=0.4.14; extra == "jax"
Requires-Dist: jaxlib>=0.4.14; extra == "jax"
Requires-Dist: diffrax>=0.6.2; extra == "jax"
Provides-Extra: dev
Requires-Dist: pytest; extra == "dev"
Requires-Dist: ruff; extra == "dev"
Provides-Extra: notebooks
Requires-Dist: ipywidgets; extra == "notebooks"
Requires-Dist: ipympl; extra == "notebooks"
Requires-Dist: notebook; extra == "notebooks"
Dynamic: license-file
